{
  "version": "0.2",
  "$schema": "https://raw.githubusercontent.com/streetsidesoftware/cspell/master/cspell.schema.json",
  "language": "en",
  "words": [
    "abccc",
    "addrs",
    "bitauth",
    "bitjson",
    "charsets",
    "cimg",
    "circleci",
    "codecov",
    "commitlint",
    "dependabot",
    "dimden",
    "dotfile",
    "dotfiles",
    "editorconfig",
    "encodeurl",
    "Errback",
    "esnext",
    "etag",
    "execa",
    "exponentiate",
    "Fastify",
    "fileupload",
    "globby",
    "hono",
    "libauth",
    "mkactivity",
    "mkcalendar",
    "mkcol",
    "mkdir",
    "mountpath",
    "Nigro",
    "nosniff",
    "prettierignore",
    "propfind",
    "proppatch",
    "proxyaddr",
    "quasis",
    "runtimes",
    "Ryzen",
    "sandboxed",
    "transpiled",
    "tseep",
    "tsoa",
    "typedoc",
    "typeis",
    "unoptimized",
    "untracked",
    "uppercased",
    "Uwebsockets"
  ],
  "flagWords": [],
  "ignorePaths": [
    "package.json",
    "package-lock.json",
    "yarn.lock",
    "tsconfig.json",
    "node_modules/**"
  ]
}
